tenro/__init__.py
tenro/py.typed
tenro/capabilities/__init__.py
tenro/capabilities/coverage.py
tenro/capabilities/executed_collector.py
tenro/capabilities/exporter.py
tenro/capabilities/global_registry.py
tenro/capabilities/renderer.py
tenro/capabilities/reporting.py
tenro/capabilities/scenario.py
tenro/capabilities/types.py
tenro/client/__init__.py
tenro/client/_client.py
tenro/client/init.py
tenro/client/prompt.py
tenro/construct/__init__.py
tenro/construct/construct.py
tenro/construct/decorators.py
tenro/construct/in_memory_store.py
tenro/construct/http/__init__.py
tenro/construct/http/interceptor.py
tenro/construct/http/builders/__init__.py
tenro/construct/http/builders/anthropic.py
tenro/construct/http/builders/base.py
tenro/construct/http/builders/factory.py
tenro/construct/http/builders/gemini.py
tenro/construct/http/builders/openai.py
tenro/construct/http/registry/__init__.py
tenro/construct/http/registry/builtin.py
tenro/construct/http/registry/exceptions.py
tenro/construct/http/registry/plugins.py
tenro/construct/http/registry/registry.py
tenro/construct/http/registry/types.py
tenro/construct/http/schemas/__init__.py
tenro/construct/http/schemas/anthropic/__init__.py
tenro/construct/http/schemas/anthropic/messages.py
tenro/construct/http/schemas/gemini/__init__.py
tenro/construct/http/schemas/gemini/generate_content.py
tenro/construct/http/schemas/openai/__init__.py
tenro/construct/http/schemas/openai/chat_completions.py
tenro/construct/http/test_vectors/__init__.py
tenro/construct/http/test_vectors/loader.py
tenro/construct/http/test_vectors/anthropic/messages/text_response.json
tenro/construct/http/test_vectors/anthropic/messages/tool_use_response.json
tenro/construct/http/test_vectors/gemini/generate_content/function_call_response.json
tenro/construct/http/test_vectors/gemini/generate_content/text_response.json
tenro/construct/http/test_vectors/openai/chat_completions/text_response.json
tenro-0.1.5.dist-info/METADATA
tenro-0.1.5.dist-info/WHEEL
tenro-0.1.5.dist-info/entry_points.txt
tenro-0.1.5.dist-info/licenses/LICENSE
tenro-0.1.5.dist-info/RECORD
