Metadata-Version: 2.4
Name: tenro
Version: 0.1.5
Summary: A modern multi-agent AI testing framework
Project-URL: Homepage, https://github.com/tenro-ai/tenro-python
Project-URL: Repository, https://github.com/tenro-ai/tenro-python
Project-URL: Changelog, https://github.com/tenro-ai/tenro-python/releases
Author-email: Tenro <support@tenro.ai>
Maintainer-email: Tenro <support@tenro.ai>
License-Expression: Apache-2.0
License-File: LICENSE
Keywords: agent-testing,ai-agents,llm,llm-testing,multi-agent,pytest,pytest-plugin,simulation,testing,tracing
Classifier: Development Status :: 3 - Alpha
Classifier: Framework :: Pytest
Classifier: Intended Audience :: Developers
Classifier: License :: OSI Approved :: Apache Software License
Classifier: Programming Language :: Python :: 3
Classifier: Programming Language :: Python :: 3.11
Classifier: Programming Language :: Python :: 3.12
Classifier: Programming Language :: Python :: 3.13
Classifier: Programming Language :: Python :: 3.14
Classifier: Topic :: Scientific/Engineering :: Artificial Intelligence
Classifier: Topic :: Software Development :: Quality Assurance
Classifier: Topic :: Software Development :: Testing
Classifier: Topic :: Software Development :: Testing :: Unit
Classifier: Typing :: Typed
Requires-Python: >=3.11
Requires-Dist: httpx>=0.28.1
Requires-Dist: pydantic>=2.11.9
Requires-Dist: respx>=0.22.0
Requires-Dist: rich>=14.2.0
Requires-Dist: uuid-utils>=0.12.0
